labx/__init__.py
labx/cli.py
labx-0.1.1.dist-info/LICENSE
labx-0.1.1.dist-info/METADATA
labx-0.1.1.dist-info/WHEEL
labx-0.1.1.dist-info/entry_points.txt
labx-0.1.1.dist-info/top_level.txt
labx-0.1.1.dist-info/RECORD
