Metadata-Version: 2.2
Name: labx
Version: 0.1.1
Summary: A CLI to browse
Home-page: https://github.com/hahaha/labx
Author: ChatGPT
Author-email: gpt@chat.com
Keywords: cli,pastebin,downloader,curses
Classifier: Programming Language :: Python :: 3
Classifier: Operating System :: OS Independent
Requires-Python: >=3.6
License-File: LICENSE
Requires-Dist: requests
Requires-Dist: windows-curses; platform_system == "Windows"
Dynamic: author
Dynamic: author-email
Dynamic: classifier
Dynamic: description
Dynamic: description-content-type
Dynamic: home-page
Dynamic: keywords
Dynamic: requires-dist
Dynamic: requires-python
Dynamic: summary
